BCGM_Python/__init__.py
BCGM_Python/__main__.py
BCGM_Python/feature_handler.py
BCGM_Python/helper.py
BCGM_Python/encrypt_decrypt/__init__.py
BCGM_Python/encrypt_decrypt/decrypt_pack.py
BCGM_Python/encrypt_decrypt/encrypt_pack.py
BCGM_Python/file_mods/__init__.py
BCGM_Python/file_mods/enemy_mod.py
BCGM_Python/file_mods/stage_mod.py
BCGM_Python/file_mods/unit_mod.py
BCGM_Python/files/version.txt
battle_cats_game_modder-1.0.6.dist-info/LICENSE
battle_cats_game_modder-1.0.6.dist-info/METADATA
battle_cats_game_modder-1.0.6.dist-info/WHEEL
battle_cats_game_modder-1.0.6.dist-info/top_level.txt
battle_cats_game_modder-1.0.6.dist-info/RECORD
