Metadata-Version: 2.1
Name: battle-cats-game-modder
Version: 1.0.6
Summary: A battle cats tool for modifying, encrypting, and decrypting game files
Home-page: https://github.com/fieryhenry/BCGM-Python
Author: fieryhenry
Classifier: Programming Language :: Python :: 3
Classifier: License :: OSI Approved :: MIT License
Classifier: Operating System :: OS Independent
Requires-Python: >=3.6
License-File: LICENSE
Requires-Dist: colored ==1.4.4
Requires-Dist: tk
Requires-Dist: alive-progress
Requires-Dist: pycryptodomex
Requires-Dist: requests
